nti.nikola_chameleon-1.0.0-py3.6-nspkg.pth
nti/nikola_chameleon/__init__.py
nti/nikola_chameleon/adapters.py
nti/nikola_chameleon/configure.zcml
nti/nikola_chameleon/feeds.py
nti/nikola_chameleon/interfaces.py
nti/nikola_chameleon/macro.py
nti/nikola_chameleon/meta.zcml
nti/nikola_chameleon/nti.nikola_chameleon.plugin
nti/nikola_chameleon/plugin.py
nti/nikola_chameleon/request.py
nti/nikola_chameleon/template.py
nti/nikola_chameleon/view.py
nti/nikola_chameleon/viewlets.py
nti/nikola_chameleon/zcml.py
nti/nikola_chameleon/tests/__init__.py
nti/nikola_chameleon/tests/test_interfaces.py
nti/nikola_chameleon/tests/test_render.py
nti/nikola_chameleon/tests/test_zcml.py
nti/nikola_chameleon/tests/testsite/README.txt
nti/nikola_chameleon/tests/testsite/conf.py
nti/nikola_chameleon/tests/testsite/files/favicon.ico
nti/nikola_chameleon/tests/testsite/files/images/nikola.png
nti/nikola_chameleon/tests/testsite/galleries/demo/exclude.meta
nti/nikola_chameleon/tests/testsite/galleries/demo/index.txt
nti/nikola_chameleon/tests/testsite/galleries/demo/tesla2_lg.jpg
nti/nikola_chameleon/tests/testsite/galleries/demo/tesla4_lg.jpg
nti/nikola_chameleon/tests/testsite/galleries/demo/tesla_conducts_lg.jpg
nti/nikola_chameleon/tests/testsite/galleries/demo/tesla_lightning1_lg.jpg
nti/nikola_chameleon/tests/testsite/galleries/demo/tesla_lightning2_lg.jpg
nti/nikola_chameleon/tests/testsite/galleries/demo/tesla_tower1_lg.jpg
nti/nikola_chameleon/tests/testsite/images/frontispiece.jpg
nti/nikola_chameleon/tests/testsite/images/illus_001.jpg
nti/nikola_chameleon/tests/testsite/listings/hello.py
nti/nikola_chameleon/tests/testsite/pages/1.rst
nti/nikola_chameleon/tests/testsite/pages/alist.rst
nti/nikola_chameleon/tests/testsite/pages/bootstrap-demo.rst
nti/nikola_chameleon/tests/testsite/pages/charts.txt
nti/nikola_chameleon/tests/testsite/pages/creating-a-theme.rst
nti/nikola_chameleon/tests/testsite/pages/dr-nikolas-vendetta.rst
nti.nikola_chameleon-1.0.0.dist-info/METADATA
nti.nikola_chameleon-1.0.0.dist-info/RECORD
nti.nikola_chameleon-1.0.0.dist-info/WHEEL
nti.nikola_chameleon-1.0.0.dist-info/entry_points.txt
nti.nikola_chameleon-1.0.0.dist-info/namespace_packages.txt
nti.nikola_chameleon-1.0.0.dist-info/top_level.txt
nti.nikola_chameleon-1.0.0.dist-info/zip-safe
