Metadata-Version: 2.1
Name: nti.nikola-chameleon
Version: 1.0.0
Summary: NTI Nikola Chameleon
Home-page: https://github.com/NextThought/nti.nikola_chameleon
Author: Jason Madden
Author-email: jason@nextthought.com
License: Apache
Keywords: nikola chameleon template blog static
Platform: UNKNOWN
Classifier: Intended Audience :: Developers
Classifier: Natural Language :: English
Classifier: Operating System :: OS Independent
Classifier: Programming Language :: Python :: 3
Classifier: Programming Language :: Python :: 3.5
Classifier: Programming Language :: Python :: 3.6
Classifier: Programming Language :: Python :: Implementation :: CPython
Classifier: Programming Language :: Python :: Implementation :: PyPy
Requires-Python: >=3.5
Provides-Extra: docs
Provides-Extra: test
Requires-Dist: setuptools
Requires-Dist: Chameleon
Requires-Dist: z3c.pt
Requires-Dist: z3c.macro
Requires-Dist: z3c.template
Requires-Dist: z3c.ptcompat
Requires-Dist: zope.browserpage
Requires-Dist: zope.interface
Requires-Dist: zope.dottedname
Requires-Dist: zope.viewlet
Requires-Dist: nikola (>=8.0.0b2)
Provides-Extra: docs
Requires-Dist: Sphinx; extra == 'docs'
Requires-Dist: repoze.sphinx.autointerface; extra == 'docs'
Requires-Dist: sphinx-rtd-theme; extra == 'docs'
Provides-Extra: test
Requires-Dist: nti.testing; extra == 'test'
Requires-Dist: zope.testrunner; extra == 'test'
